niiif-niiif.py
niiif.py
niiif_niiif-0.3.1.dist-info/LICENCE.md
niiif_niiif-0.3.1.dist-info/METADATA
niiif_niiif-0.3.1.dist-info/WHEEL
niiif_niiif-0.3.1.dist-info/top_level.txt
niiif_niiif-0.3.1.dist-info/RECORD
