Metadata-Version: 2.1
Name: niiif-niiif
Version: 0.3.1
Summary: Création et dépôt de manifestes IIIF pour des données déposées sur Nakala
Home-page: https://gitlab.huma-num.fr/jpressac/niiif-niiif
Author: Jean-Baptiste Pressac
License: UNKNOWN
Project-URL: Issues, https://gitlab.huma-num.fr/jpressac/niiif-niiif/-/issues
Project-URL: CI, https://gitlab.huma-num.fr/jpressac/niiif-niiif/-/pipelines
Project-URL: Changelog, https://gitlab.huma-num.fr/jpressac/niiif-niiif/-/blob/master/CHANGELOG.md
Platform: UNKNOWN
Classifier: Programming Language :: Python :: 3
Classifier: License :: OSI Approved :: GNU General Public License (GPL)
Classifier: Operating System :: OS Independent
Requires-Python: >=3.6
License-File: LICENCE.md
Requires-Dist: requests
Requires-Dist: tqdm
